futuremaker/__init__.py
futuremaker/algo.py
futuremaker/barlist.py
futuremaker/bitmex_api.py
futuremaker/bitmex_ws.py
futuremaker/candle_handler.py
futuremaker/collections.py
futuremaker/config.py
futuremaker/constants.py
futuremaker/data_ingest.py
futuremaker/exception.py
futuremaker/indicators.py
futuremaker/log.py
futuremaker/nexus_mock.py
futuremaker/telegram_adapter.py
futuremaker/utils.py
futuremaker/zigzag.py
futuremaker/bitmex/__init__.py
futuremaker/bitmex/bot.py
futuremaker/bitmex/nexus.py
futuremaker-0.0.11.dist-info/METADATA
futuremaker-0.0.11.dist-info/WHEEL
futuremaker-0.0.11.dist-info/top_level.txt
futuremaker-0.0.11.dist-info/RECORD
