Metadata-Version: 2.1
Name: futuremaker
Version: 0.0.11
Summary: Cryptocurrency trading library
Home-page: https://github.com/gncloud/futuremaker
Author: SongSangWook
Author-email: swsong@gncloud.kr
License: UNKNOWN
Platform: UNKNOWN
Classifier: Programming Language :: Python :: 3
Classifier: License :: OSI Approved :: MIT License
Classifier: Operating System :: OS Independent
Requires-Dist: bitmex
Requires-Dist: websockets
Requires-Dist: aiohttp
Requires-Dist: asyncio
Requires-Dist: pandas
Requires-Dist: pytz
Requires-Dist: python-telegram-bot
Requires-Dist: ccxt
